indico_livesync_debug/__init__.py
indico_livesync_debug/backend.py
indico_livesync_debug/plugin.py
indico_plugin_livesync_debug-3.3.dist-info/METADATA
indico_plugin_livesync_debug-3.3.dist-info/WHEEL
indico_plugin_livesync_debug-3.3.dist-info/entry_points.txt
indico_plugin_livesync_debug-3.3.dist-info/top_level.txt
indico_plugin_livesync_debug-3.3.dist-info/RECORD
