Metadata-Version: 2.1
Name: indico-plugin-livesync-debug
Version: 3.3
Summary: Debug target for the Indico LiveSync plugin
Home-page: https://github.com/indico/indico-plugins
Author: Indico Team
Author-email: indico-team@cern.ch
License: MIT
Classifier: Environment :: Plugins
Classifier: Environment :: Web Environment
Classifier: License :: OSI Approved :: MIT License
Classifier: Programming Language :: Python :: 3.12
Requires-Python: <3.13,>=3.12.2
Requires-Dist: indico >=3.3
Requires-Dist: indico-plugin-livesync >=3.3.dev0
